<!-- <?xml version="1.0" encoding="UTF-8"?>
<beans xmlns="http://www.springframework.org/schema/beans"
	xmlns:xsi="http://www.w3.org/2001/XMLSchema-instance"
	xmlns:p="http://www.springframework.org/schema/p"
	xmlns:context="http://www.springframework.org/schema/context"
	xmlns:tx="http://www.springframework.org/schema/tx"
	xmlns:mvc="http://www.springframework.org/schema/mvc"
	xsi:schemaLocation="http://www.springframework.org/schema/mvc http://www.springframework.org/schema/mvc/spring-mvc.xsd
		http://www.springframework.org/schema/beans http://www.springframework.org/schema/beans/spring-beans.xsd
		http://www.springframework.org/schema/context http://www.springframework.org/schema/context/spring-context.xsd
		http://www.springframework.org/schema/tx http://www.springframework.org/schema/tx/spring-tx.xsd">

    <context:annotation-config/>
	<context:component-scan base-package="tw.eeit117.wematch" />
	<tx:annotation-driven transaction-manager="transactionManager" />
	<mvc:annotation-driven />
	
    <bean id="sqlserverdataSource" class="org.springframework.jndi.JndiObjectFactoryBean">
       <property name="jndiName" value="java:comp/env/connectSQLServerJdbc/WeMatch"/>
    </bean>
    
    <bean id="sessionFactory" class="org.springframework.orm.hibernate5.LocalSessionFactoryBean">
       <property name="dataSource" ref="sqlserverdataSource"/>
       <property name="packagesToScan" value="tw.eeit117.wematch.model" />
       <property name="hibernateProperties">
       		<props>
       			<prop key="hibernate.dialect">org.hibernate.dialect.SQLServerDialect</prop>
       			<prop key="hibernate.show_sql">true</prop>
       			<prop key="hibernate.format_sql">true</prop>
       			<prop key="hibernate.current_session_context_class">thread</prop>
       		</props>
       </property>

    </bean>
    
    <bean id="transactionManager" class="org.springframework.orm.hibernate5.HibernateTransactionManager">
    	<property name="sessionFactory" ref="sessionFactory" />
    </bean>

</beans> -->